GeneCloud/__init__.py
GeneCloud/__main__.py
GeneCloud/genecloud.py
GeneCloud/pics/alice
GeneCloud/pics/brain
GeneCloud/pics/fish
GeneCloud/pics/square
GeneCloud/pics/stormtrooper
gene_cloud-0.0.7.dist-info/DESCRIPTION.rst
gene_cloud-0.0.7.dist-info/METADATA
gene_cloud-0.0.7.dist-info/RECORD
gene_cloud-0.0.7.dist-info/WHEEL
gene_cloud-0.0.7.dist-info/entry_points.txt
gene_cloud-0.0.7.dist-info/metadata.json
gene_cloud-0.0.7.dist-info/top_level.txt
