Metadata-Version: 2.0
Name: gene-cloud
Version: 0.0.7
Summary: An enhancer for PaperBlast
Home-page: https://github.com/sradiouy/Gene-Cloud
Author: Santiago Radio
Author-email: sradio91@gmail.com
License: MIT
Keywords: genecloud,paperblast,uniprot,wordcloud,gene ontology
Platform: UNKNOWN
Classifier: Development Status :: 5 - Production/Stable
Classifier: Environment :: Console
Classifier: Intended Audience :: Science/Research
Classifier: License :: OSI Approved :: MIT License
Classifier: Operating System :: Unix
Classifier: Natural Language :: English
Classifier: Programming Language :: Python :: 3
Classifier: Topic :: Scientific/Engineering :: Bio-Informatics
Requires-Python: >=3.5
Requires-Dist: mygene
Requires-Dist: requires
